lez_20221005/CombFunction.d/CombFunction.vhd
entity CombFunction is
    port (a, b, c : in bit; z : out bit);
end entity CombFunction;

architecture expression of CombFunction is
    signal d : bit;
begin
    z <= d or c after 4 ns;
    d <= a and b after 5 ns;
end architecture expression;

lez_20221005/CombFunction.d/Test_CombFunction.vhd
entity Test_CombFunction is
end entity Test_CombFunction;

architecture simple of Test_CombFunction is
    signal a, b, c, z : bit;
begin
    g1: entity work.CombFunction port map (a => a, b => b, c => c, z => z);

    a <= '0', '1' after 100 ns, '0' after 200 ns, '0' after 300 ns;
    b <= '0', '1' after 150 ns, '0' after 250 ns, '0' after 300 ns;
    c <= '1', '0' after 100 ns;
end architecture simple;

lez_20221005/CombFunction.d/out.vcd
$date
  Wed Oct  5 12:10:45 2022
$end
$version
  GHDL v0
$end
$timescale
  1 fs
$end
$scope module standard $end
$upscope $end
$scope module test_combfunction $end
$var reg 1 ! a $end
$var reg 1 " b $end
$var reg 1 # c $end
$var reg 1 $ z $end
$scope module g1 $end
$var reg 1 % a $end
$var reg 1 & b $end
$var reg 1 ' c $end
$var reg 1 ( z $end
$var reg 1 ) d $end
$upscope $end
$upscope $end
$enddefinitions $end
#0
0!
0"
1#
0$
0%
0&
1'
0(
0)
#4000000
1$
1(
#5000000
#100000000
1!
0#
1%
0'
#104000000
0$
0(
#105000000
#150000000
1"
1&
#155000000
1)
#159000000
1$
1(
#200000000
0!
0%
#205000000
0)
#209000000
0$
0(
#250000000
0"
0&
