lez_20221005/Multiplexer.d/Multiplexer.vhd
entity Multiplexer is
    port (a, b, s : in bit; y : out bit);
end entity;

architecture eqz of Multiplexer is
    signal d, e, c : bit;
begin
    d <= a and s after 2 ns;
    e <= not s after 2 ns;
    c <= b and e after 2 ns;
    y <= d or c after 2 ns;
end architecture;

lez_20221005/Multiplexer.d/Test_Multiplexer.vhd
entity Test is
end entity;

architecture simple of Test is
    signal a, b, s, y : bit;
begin
    m1: entity work.Multiplexer port map (a => a, b => b, s => s, y => y);

    a <= '1';
    b <= '1';
    s <= '1', '0' after 100 ns, '1' after 200 ns;
end architecture;

lez_20221005/Multiplexer.d/out.vcd
$date
  Wed Oct  5 12:23:54 2022
$end
$version
  GHDL v0
$end
$timescale
  1 fs
$end
$scope module standard $end
$upscope $end
$scope module test $end
$var reg 1 ! a $end
$var reg 1 " b $end
$var reg 1 # s $end
$var reg 1 $ y $end
$scope module m1 $end
$var reg 1 % a $end
$var reg 1 & b $end
$var reg 1 ' s $end
$var reg 1 ( y $end
$var reg 1 ) d $end
$var reg 1 * e $end
$var reg 1 + c $end
$upscope $end
$upscope $end
$enddefinitions $end
#0
1!
1"
1#
0$
1%
1&
1'
0(
0)
0*
0+
#2000000
0(
1)
#4000000
1$
1(
#100000000
0#
0'
#102000000
0)
1*
#104000000
0$
0(
1+
#106000000
1$
1(
#200000000
1#
1'
#202000000
1)
0*
#204000000
1(
0+
#206000000
1(
